[
    {
        "title": "Encorajamento a Jerusalém. a.C. 706.",
        "verses": [
            1,
            2,
            3,
            4,
            5,
            6
        ]
    },
    {
        "title": "A Aproximação do Messias. a.C. 706.",
        "verses": [
            7,
            8,
            9,
            10,
            11,
            12
        ]
    },
    {
        "title": "A Humilhação do Messias. a.C. 706.",
        "verses": [
            13,
            14,
            15
        ]
    }
]