[
    {
        "title": "Morte dos Justos. a.C. 706.",
        "verses": [
            1,
            2
        ]
    },
    {
        "title": "Uma Acusação contra o Povo. a.C. 706.",
        "verses": [
            3,
            4,
            5,
            6,
            7,
            8,
            9,
            10,
            11,
            12
        ]
    },
    {
        "title": "Vaidade dos Ídolos; Grandeza Divina e Condescendência. a.C. 706.",
        "verses": [
            13,
            14,
            15,
            16
        ]
    },
    {
        "title": "A Divina Paciência e Misericórdia. a.C. 706.",
        "verses": [
            17,
            18,
            19,
            20,
            21
        ]
    }
]